{
	"zh": {
		"change_email_form_validate_empty_email": "请输入邮箱",
		"change_email_form_validate_error_email": "请输入正确的邮箱",
		"change_email_form_validate_empty_vcode": "请输入验证码",
		"change_email_form_validate_six_vcode": "请输入6位数验证码",
		"change_email_form_validate_empty_trade_password": "请输入资金密码",
		"change_email_form_send_success": "发送成功， 请查收",
		"change_email_form_label_email": "新邮箱：",
		"change_email_form_label_vcode": "新邮箱验证码：",
		"change_email_form_label_trade_password": "资金密码",
		"change_email_form_cancel": "取消",
		"change_email_form_confirm": "确认修改",
		"change_email_form_success": "修改成功！",
		"change_email_form_label_formal_vcode": "原邮箱验证码：",
		"input_button_focus": "若验证码邮件没有顺利到达您的收件箱，请注意检查垃圾箱内的邮件",
		"input_new_email": "请输入新邮箱",
		"pc_input_new_email": "请输入新邮箱地址",
		"input_old_vcode": "请输入原邮箱验证码",
		"input_new_vcode": "请输入新邮箱验证码"
	},
	"en": {
		"change_email_form_validate_empty_email": "Please enter your email address",
		"change_email_form_validate_error_email": "Please enter a valid email address",
		"change_email_form_validate_empty_vcode": "Please enter the verification code",
		"change_email_form_validate_six_vcode": "Please enter the 6-digit verification code",
		"change_email_form_validate_empty_trade_password": "Please enter fund password",
		"change_email_form_send_success": "Successfully sent, please check",
		"change_email_form_label_email": "New email address:",
		"change_email_form_label_vcode": "New email verification code:",
		"change_email_form_label_trade_password": "Fund password",
		"change_email_form_cancel": "Cancel",
		"change_email_form_confirm": "Confirm change",
		"change_email_form_success": "Successfully changed!",
		"change_email_form_label_formal_vcode": "Old verification code:",
		"input_button_focus": "If you do not receive an email, please check your junk or spam folders.",
		"input_new_email": "Please enter a new Email address",
		"pc_input_new_email": "Please enter new Email address",
		"input_old_vcode": "Please enter the old verification code",
		"input_new_vcode": "Please enter the new verification code"
	},
	"ko": {
		"change_email_form_validate_empty_email": "이메일을 입력해주세요",
		"change_email_form_validate_error_email": "정확한 이메일을 입력해주세요",
		"change_email_form_validate_empty_vcode": "인증 번호를 입력해주세요",
		"change_email_form_validate_six_vcode": "6자 인증 번호를 입력해주세요",
		"change_email_form_validate_empty_trade_password": "출금 비밀번호 입력해주세요",
		"change_email_form_send_success": "발송성공",
		"change_email_form_label_email": "새 이메일：",
		"change_email_form_label_vcode": "새 이메일의 인증코드 발송：",
		"change_email_form_label_trade_password": "출금 비밀번호",
		"change_email_form_cancel": "취소",
		"change_email_form_confirm": "변경",
		"change_email_form_success": "수정 성공！",
		"change_email_form_label_formal_vcode": "기존 이메일 인증코드 발송：",
		"input_button_focus": "인증 메일을 받지 못한 경우 스팸 메일함도 확인해주세요",
		"input_new_email": "새 이메일을 입력해주세요",
		"pc_input_new_email": "새로운 이메일 주소를 입력해주세요",
		"input_old_vcode": "기존 이메일 인증코드를 입력해주세요",
		"input_new_vcode": "새 이메일 인증코드를 입력해주세요"
	},
	"ja": {
		"change_email_form_validate_empty_email": "メールアドレスを入力してください",
		"change_email_form_validate_error_email": "正しいメールアドレスを入力してください",
		"change_email_form_validate_empty_vcode": "認証コードを入力してください",
		"change_email_form_validate_six_vcode": "6桁の認証コードを入力してください",
		"change_email_form_validate_empty_trade_password": "出金パスワードを入力してください",
		"change_email_form_send_success": "送信成功、ご確認ください",
		"change_email_form_label_email": "新しいメールアドレス：",
		"change_email_form_label_vcode": "新しいメールの認証コード：",
		"change_email_form_label_trade_password": "出金パスワード",
		"change_email_form_cancel": "取り消す",
		"change_email_form_confirm": "修正の確認",
		"change_email_form_success": "修正完了！",
		"change_email_form_label_formal_vcode": "旧メールアドレスの認証コード：",
		"input_button_focus": "メールが届かない可能性があるため、一度「迷惑メール」フォルダをご確認ください",
		"input_new_email": "新しいメールアドレスを入力してください",
		"pc_input_new_email": "新しいメールアドレスをご記入ください",
		"input_old_vcode": "メールの元検証コードを入力してください",
		"input_new_vcode": "メールの新検証コードを入力してください"
	},
	"ru": {
		"change_email_form_validate_empty_email": "Пожалуйста, введите свой адрес электронной почты",
		"change_email_form_validate_error_email": "Пожалуйста, введите действующий адрес электронной почты",
		"change_email_form_validate_empty_vcode": "Пожалуйста, введите проверочный код",
		"change_email_form_validate_six_vcode": "Введите 6-значный проверочный код",
		"change_email_form_validate_empty_trade_password": "Пожалуйста, введите пароль фонда",
		"change_email_form_send_success": "Успешно отправлено, пожалуйста, проверьте",
		"change_email_form_label_email": "Новый E-mail:",
		"change_email_form_label_vcode": "Код подтверждения нового почтового ящика:",
		"change_email_form_label_trade_password": "Пароль фонда",
		"change_email_form_cancel": "Отмена",
		"change_email_form_confirm": "Подтвердите изменения",
		"change_email_form_success": "Успешно изменен!",
		"change_email_form_label_formal_vcode": "Оригинальный код подтверждения электронной почты:",
		"input_button_focus": "Почта может не дойти до вашего почтового ящика гладко, пожалуйста, проверьте информацию в мусор",
		"input_new_email": "Введите новый адрес электронной почты",
		"pc_input_new_email": "请输入新邮箱地址",
		"input_old_vcode": "Введите первоначальный код подтверждения электронной почты",
		"input_new_vcode": "Введите новый код подтверждения электронной почты"
	},
	"vi": {
		"change_email_form_validate_empty_email": "Vui lòng nhập địa chỉ email của bạn",
		"change_email_form_validate_error_email": "Vui lòng nhập địa chỉ email hợp lệ",
		"change_email_form_validate_empty_vcode": "Vui lòng nhập mã xác nhận",
		"change_email_form_validate_six_vcode": "Vui lòng nhập mã xác minh gồm 6 chữ số",
		"change_email_form_validate_empty_trade_password": "Vui lòng nhập mật tài khoản",
		"change_email_form_send_success": "đã gửi, vui lòng kiểm tra lại",
		"change_email_form_label_email": "Email mới：",
		"change_email_form_label_vcode": "Mã xác nhận Email mới：",
		"change_email_form_label_trade_password": "mật khẩu tài khoản",
		"change_email_form_cancel": "Hủy bỏ",
		"change_email_form_confirm": "xác nhận sửa",
		"change_email_form_success": "sử thành công！",
		"change_email_form_label_formal_vcode": "Mã xác nhận Email cũ：",
		"input_button_focus": "nếu vẫn chưa nhận được mã xác nhận, vui lòng kiểm tra lại hộp thư rác",
		"input_new_email": "Vui lòng nhập Email mới",
		"pc_input_new_email": "vui lòng nhập địa chỉ Email mới",
		"input_old_vcode": "vui lòng nhập mã xác nhận Email cũ",
		"input_new_vcode": "vui lòng nhập mã xác nhận Email mới"
	},
	"zh-Hant": {
		"change_email_form_validate_empty_email": "請輸入郵箱",
		"change_email_form_validate_error_email": "請輸入正確的郵箱",
		"change_email_form_validate_empty_vcode": "請輸入驗證碼",
		"change_email_form_validate_six_vcode": "請輸入6位數驗證碼",
		"change_email_form_validate_empty_trade_password": "請輸入資金密碼",
		"change_email_form_send_success": "發送成功， 請查收",
		"change_email_form_label_email": "新郵箱：",
		"change_email_form_label_vcode": "新郵箱驗證碼：",
		"change_email_form_label_trade_password": "資金密碼",
		"change_email_form_cancel": "取消",
		"change_email_form_confirm": "確認修改",
		"change_email_form_success": "修改成功！",
		"change_email_form_label_formal_vcode": "原郵箱驗證碼：",
		"input_button_focus": "郵件可能無法順利到達您的郵箱，請注意檢查垃圾箱內的信息",
		"input_new_email": "請輸入新郵箱",
		"pc_input_new_email": "請輸入新郵箱地址",
		"input_old_vcode": "請輸入原郵箱驗證碼",
		"input_new_vcode": "請輸入新郵箱驗證碼"
	}
}
